octasonic/__init__.py
octasonic/octasonic.py
octasonic-1.1.dist-info/LICENSE.txt
octasonic-1.1.dist-info/METADATA
octasonic-1.1.dist-info/WHEEL
octasonic-1.1.dist-info/top_level.txt
octasonic-1.1.dist-info/RECORD
